<?xml version="1.0" encoding="utf-8"?>
<TextureAtlas imagePath="SheAwakens.png">
  <!-- Created with Adobe Animate version 21.0.6.41649 -->
  <!-- http://www.adobe.com/products/animate.html -->
  <SubTexture name="SheAwakens0000" x="4" y="4" width="600" height="285" frameX="-33" frameY="-14" frameWidth="666" frameHeight="313" />
  <SubTexture name="SheAwakens0001" x="4" y="4" width="600" height="285" frameX="-33" frameY="-14" frameWidth="666" frameHeight="313" />
  <SubTexture name="SheAwakens0002" x="4" y="4" width="600" height="285" frameX="-33" frameY="-14" frameWidth="666" frameHeight="313" />
  <SubTexture name="SheAwakens0003" x="608" y="4" width="600" height="285" frameX="-33" frameY="-14" frameWidth="666" frameHeight="313" />
  <SubTexture name="SheAwakens0004" x="1212" y="4" width="651,5" height="306" frameX="-7,5" frameY="-3,5" frameWidth="666" frameHeight="313" />
  <SubTexture name="SheAwakens0005" x="1212" y="4" width="651,5" height="306" frameX="-7,5" frameY="-3,5" frameWidth="666" frameHeight="313" />
  <SubTexture name="SheAwakens0006" x="1212" y="4" width="651,5" height="306" frameX="-7,5" frameY="-3,5" frameWidth="666" frameHeight="313" />
  <SubTexture name="SheAwakens0007" x="4" y="314" width="651,5" height="306" frameX="-7,5" frameY="-3,5" frameWidth="666" frameHeight="313" />
  <SubTexture name="SheAwakens0008" x="659,5" y="314" width="666" height="313" />
  <SubTexture name="SheAwakens0009" x="659,5" y="314" width="666" height="313" />
  <SubTexture name="SheAwakens0010" x="659,5" y="314" width="666" height="313" />
  <SubTexture name="SheAwakens0011" x="1329,5" y="314" width="666" height="313" />
  <SubTexture name="SheAwakens0012" x="4" y="631" width="545" height="230" frameX="-59,5" frameY="-40,5" frameWidth="666" frameHeight="313" />
  <SubTexture name="SheAwakens0013" x="4" y="631" width="545" height="230" frameX="-59,5" frameY="-40,5" frameWidth="666" frameHeight="313" />
  <SubTexture name="SheAwakens0014" x="4" y="631" width="545" height="230" frameX="-59,5" frameY="-40,5" frameWidth="666" frameHeight="313" />
  <SubTexture name="SheAwakens0015" x="4" y="631" width="545" height="230" frameX="-59,5" frameY="-40,5" frameWidth="666" frameHeight="313" />
  <SubTexture name="SheAwakens0016" x="553" y="631" width="545" height="230" frameX="-59,5" frameY="-40,5" frameWidth="666" frameHeight="313" />
  <SubTexture name="SheAwakens0017" x="553" y="631" width="545" height="230" frameX="-59,5" frameY="-40,5" frameWidth="666" frameHeight="313" />
  <SubTexture name="SheAwakens0018" x="553" y="631" width="545" height="230" frameX="-59,5" frameY="-40,5" frameWidth="666" frameHeight="313" />
  <SubTexture name="SheAwakens0019" x="553" y="631" width="545" height="230" frameX="-59,5" frameY="-40,5" frameWidth="666" frameHeight="313" />
  <SubTexture name="SheAwakens0020" x="1102" y="631" width="545" height="230" frameX="-59,5" frameY="-40,5" frameWidth="666" frameHeight="313" />
  <SubTexture name="SheAwakens0021" x="1102" y="631" width="545" height="230" frameX="-59,5" frameY="-40,5" frameWidth="666" frameHeight="313" />
  <SubTexture name="SheAwakens0022" x="1102" y="631" width="545" height="230" frameX="-59,5" frameY="-40,5" frameWidth="666" frameHeight="313" />
  <SubTexture name="SheAwakens0023" x="1102" y="631" width="545" height="230" frameX="-59,5" frameY="-40,5" frameWidth="666" frameHeight="313" />
  <SubTexture name="SheAwakens0024" x="4" y="865" width="545" height="230" frameX="-59,5" frameY="-40,5" frameWidth="666" frameHeight="313" />
  <SubTexture name="SheAwakens0025" x="4" y="865" width="545" height="230" frameX="-59,5" frameY="-40,5" frameWidth="666" frameHeight="313" />
  <SubTexture name="SheAwakens0026" x="4" y="865" width="545" height="230" frameX="-59,5" frameY="-40,5" frameWidth="666" frameHeight="313" />
  <SubTexture name="SheAwakens0027" x="4" y="865" width="545" height="230" frameX="-59,5" frameY="-40,5" frameWidth="666" frameHeight="313" />
  <SubTexture name="SheAwakens0028" x="4" y="631" width="545" height="230" frameX="-59,5" frameY="-40,5" frameWidth="666" frameHeight="313" />
  <SubTexture name="SheAwakens0029" x="4" y="631" width="545" height="230" frameX="-59,5" frameY="-40,5" frameWidth="666" frameHeight="313" />
  <SubTexture name="SheAwakens0030" x="4" y="631" width="545" height="230" frameX="-59,5" frameY="-40,5" frameWidth="666" frameHeight="313" />
  <SubTexture name="SheAwakens0031" x="4" y="631" width="545" height="230" frameX="-59,5" frameY="-40,5" frameWidth="666" frameHeight="313" />
  <SubTexture name="SheAwakens0032" x="553" y="631" width="545" height="230" frameX="-59,5" frameY="-40,5" frameWidth="666" frameHeight="313" />
  <SubTexture name="SheAwakens0033" x="553" y="631" width="545" height="230" frameX="-59,5" frameY="-40,5" frameWidth="666" frameHeight="313" />
  <SubTexture name="SheAwakens0034" x="553" y="631" width="545" height="230" frameX="-59,5" frameY="-40,5" frameWidth="666" frameHeight="313" />
  <SubTexture name="SheAwakens0035" x="553" y="631" width="545" height="230" frameX="-59,5" frameY="-40,5" frameWidth="666" frameHeight="313" />
</TextureAtlas>